leiaa/__init__.py
leiaa-0.0.0.dist-info/METADATA
leiaa-0.0.0.dist-info/WHEEL
leiaa-0.0.0.dist-info/licenses/LICENSE
leiaa-0.0.0.dist-info/RECORD
