Metadata-Version: 2.3
Name: leiaa
Version: 0.0.0
Summary: The leading investigations platform
Author: Augmetec Ltd. (A Company Registered in England & Wales)
License-File: LICENSE
Classifier: Operating System :: OS Independent
Classifier: Programming Language :: Python :: 3
Requires-Python: >=3.8
